odoo/addons/delivery_mrw/README.rst
odoo/addons/delivery_mrw/__init__.py
odoo/addons/delivery_mrw/__manifest__.py
odoo/addons/delivery_mrw/data/delivery_mrw.xml
odoo/addons/delivery_mrw/i18n/delivery_mrw.pot
odoo/addons/delivery_mrw/i18n/es.po
odoo/addons/delivery_mrw/models/__init__.py
odoo/addons/delivery_mrw/models/delivery_carrier.py
odoo/addons/delivery_mrw/models/mrw_request.py
odoo/addons/delivery_mrw/models/stock_picking.py
odoo/addons/delivery_mrw/readme/CONFIGURE.md
odoo/addons/delivery_mrw/readme/CONTRIBUTORS.md
odoo/addons/delivery_mrw/readme/DESCRIPTION.md
odoo/addons/delivery_mrw/readme/INSTALL.md
odoo/addons/delivery_mrw/readme/ROADMAP.md
odoo/addons/delivery_mrw/readme/USAGE.md
odoo/addons/delivery_mrw/security/ir.model.access.csv
odoo/addons/delivery_mrw/static/description/icon.jpg
odoo/addons/delivery_mrw/static/description/icon.png
odoo/addons/delivery_mrw/static/description/index.html
odoo/addons/delivery_mrw/tests/__init__.py
odoo/addons/delivery_mrw/tests/test_delivery_mrw.py
odoo/addons/delivery_mrw/views/delivery_mrw_view.xml
odoo/addons/delivery_mrw/views/mrw_manifest_template.xml
odoo/addons/delivery_mrw/views/stock_picking_views.xml
odoo/addons/delivery_mrw/wizard/__init__.py
odoo/addons/delivery_mrw/wizard/mrw_manifest_wizard.py
odoo/addons/delivery_mrw/wizard/mrw_manifest_wizard_views.xml
odoo_addon_delivery_mrw-17.0.1.0.0.2.dist-info/METADATA
odoo_addon_delivery_mrw-17.0.1.0.0.2.dist-info/WHEEL
odoo_addon_delivery_mrw-17.0.1.0.0.2.dist-info/top_level.txt
odoo_addon_delivery_mrw-17.0.1.0.0.2.dist-info/RECORD
